Metadata-Version: 1.0
Name: math-distributions
Version: 0.1
Summary: Gaussian and Binomail distributions
Home-page: UNKNOWN
Author: UNKNOWN
Author-email: UNKNOWN
License: UNKNOWN
Platform: UNKNOWN
